SelSik/__init__.py
SelSik-0.3.4.dist-info/LICENSE
SelSik-0.3.4.dist-info/METADATA
SelSik-0.3.4.dist-info/WHEEL
SelSik-0.3.4.dist-info/top_level.txt
SelSik-0.3.4.dist-info/RECORD
