Metadata-Version: 2.1
Name: SelSik
Version: 0.3.4
Summary: @KekikAkademi Selenium Kütüphanesi
Home-page: https://github.com/keyiflerolsun/SelSik
Author: keyiflerolsun
Author-email: keyiflerolsun@gmail.com
License: GPLv3+
Keywords: SelSik,KekikAkademi,keyiflerolsun
Classifier: Development Status :: 5 - Production/Stable
Classifier: License :: OSI Approved :: GNU General Public License v3 or later (GPLv3+)
Classifier: Programming Language :: Python :: 3
Requires-Python: >=3.11
License-File: LICENSE
Requires-Dist: setuptools
Requires-Dist: wheel
Requires-Dist: selenium
Requires-Dist: webdriver-manager
Requires-Dist: selenium-stealth
Requires-Dist: parsel
Requires-Dist: cssselect
